framework/__init__.py
framework/main.py
rlockertools/__init__.py
rlockertools/exceptions.py
rlockertools/resourcelocker.py
rlockertools/utils.py
rlockertools-0.4.5.dist-info/LICENSE.txt
rlockertools-0.4.5.dist-info/METADATA
rlockertools-0.4.5.dist-info/WHEEL
rlockertools-0.4.5.dist-info/entry_points.txt
rlockertools-0.4.5.dist-info/top_level.txt
rlockertools-0.4.5.dist-info/RECORD
