Metadata-Version: 2.1
Name: rlockertools
Version: 0.4.5
Summary: Useful tools to interact with Resource Locker Project
Home-page: https://github.com/red-hat-storage/rlockertools.git
Download-URL: https://pypi.org/project/rlockertools/
Author: Jim Erginbash
Author-email: jimshapedcoding@gmail.com
License: MIT
Keywords: Rlocker,rlocker,ResourceLocker,Python 3,Resource Locker
License-File: LICENSE.txt
Requires-Dist: requests
